<?xml version="1.0"?>
<Race_Class xmlns:xsd="http://www.w3.org/2001/XMLSchema" xmlns:xsi="http://www.w3.org/2001/XMLSchema-instance">
    <Species_Name>Ivorian</Species_Name>
    <Empire_Name>The Ivorian Empire</Empire_Name>
    <Source>Core</Source>
	<Xenophobia_Modifier>50</Xenophobia_Modifier> <!-- value between 0-100 where 0 = space commies-->
	<Militarism_Modifier>3</Militarism_Modifier> <!-- Value between 0-4 where 0 = pacifist-->
	<Expansionism_Modifier>20</Expansionism_Modifier> <!-- value between 0-100 where 0 = scared of change-->
	<Industrialism_Modifier>80</Industrialism_Modifier> <!-- Value between 0-4 where 0 = Environmentalists-->
	<Path_to_Race_Units_Class>/Races/Ivorian/IvorianUnitList.xml</Path_to_Race_Units_Class> <!-- Gives the path to this Race's units file-->
	<threatPaths> 
		<string>/Races/Ivorian/Threats/FarmRaids/FarmRaids.xml</string>
	</threatPaths> 
	<Categories>
		<Category_Class>
			<categoryName>IvorianSmallSettlement</categoryName>
			<categoryType>Settlement</categoryType>
			<snippets>
				<string>few sleek buildings</string>
				<string>beautifully designed structures</string>
				<string>few small buildings</string>
				<string>collection of pointed silver buildings</string>
			</snippets>
		</Category_Class>
	</Categories>
</Race_Class>