<?xml version="1.0"?>
<Save_Class xmlns:xsd="http://www.w3.org/2001/XMLSchema" xmlns:xsi="http://www.w3.org/2001/XMLSchema-instance">
  <saveName>NewSave</saveName>
  <height>20000</height>
  <width>20000</width>
  <systems>
    <System_Class>
      <systemName>Alpho</systemName>
      <colour>Blue_Light</colour>
      <allegiance>3</allegiance>
      <posX>-6738</posX>
      <posZ>4890</posZ>
      <nPlanets>6</nPlanets>
      <Array>
        <Planet_Class>
          <planetName>Alpho I</planetName>
          <biome>Glass World</biome>
          <biomeID>0</biomeID>
          <inhabited>false</inhabited>
          <population>851757056</population>
          <size>60</size>
          <usableSpace>0.416658729</usableSpace>
          <baseMetalsAmount>87.36432</baseMetalsAmount>
          <preciousMetalsAmount>45.4289627</preciousMetalsAmount>
          <foodAvailability>51.26663</foodAvailability>
        </Planet_Class>
        <Planet_Class>
          <planetName>Alpho II</planetName>
          <biome>Alpine</biome>
          <biomeID>0</biomeID>
          <inhabited>false</inhabited>
          <population>0</population>
          <size>78</size>
          <usableSpace>0.44165647</usableSpace>
          <baseMetalsAmount>71.2588959</baseMetalsAmount>
          <preciousMetalsAmount>119.39399</preciousMetalsAmount>
          <foodAvailability>85.34909</foodAvailability>
        </Planet_Class>
        <Planet_Class>
          <planetName>Alpho III</planetName>
          <biome>Arid</biome>
          <biomeID>0</biomeID>
          <inhabited>false</inhabited>
          <population>625212992</population>
          <size>61</size>
          <usableSpace>0.10873194</usableSpace>
          <baseMetalsAmount>46.7419662</baseMetalsAmount>
          <preciousMetalsAmount>52.22241</preciousMetalsAmount>
          <foodAvailability>54.7042</foodAvailability>
        </Planet_Class>
        <Planet_Class>
          <planetName>Alpho IV</planetName>
          <biome>Gas Giant Hydrogen</biome>
          <biomeID>8</biomeID>
          <inhabited>false</inhabited>
          <population>8164050</population>
          <size>64</size>
          <usableSpace>0</usableSpace>
          <baseMetalsAmount>0</baseMetalsAmount>
          <preciousMetalsAmount>0</preciousMetalsAmount>
          <foodAvailability>0</foodAvailability>
        </Planet_Class>
        <Planet_Class>
          <planetName>Alpho V</planetName>
          <biome>Tundra</biome>
          <biomeID>0</biomeID>
          <inhabited>false</inhabited>
          <population>286554528</population>
          <size>73</size>
          <usableSpace>0.6920877</usableSpace>
          <baseMetalsAmount>71.35863</baseMetalsAmount>
          <preciousMetalsAmount>40.95715</preciousMetalsAmount>
          <foodAvailability>0</foodAvailability>
        </Planet_Class>
        <Planet_Class>
          <planetName>Alpho VI</planetName>
          <biome>Gas Giant Hydrogen</biome>
          <biomeID>8</biomeID>
          <inhabited>false</inhabited>
          <population>0</population>
          <size>56</size>
          <usableSpace>0</usableSpace>
          <baseMetalsAmount>0</baseMetalsAmount>
          <preciousMetalsAmount>0</preciousMetalsAmount>
          <foodAvailability>0</foodAvailability>
        </Planet_Class>
      </Array>
    </System_Class>
    <System_Class>
      <systemName>Alpho</systemName>
      <colour>Blue</colour>
      <allegiance>0</allegiance>
      <posX>0</posX>
      <posZ>0</posZ>
      <nPlanets>4</nPlanets>
      <Array>
        <Planet_Class>
          <planetName>Alpho I</planetName>
          <biome>Toxic (Sulphur)</biome>
          <biomeID>18</biomeID>
          <inhabited>false</inhabited>
          <population>9846599</population>
          <size>72</size>
          <usableSpace>0.5399114</usableSpace>
          <baseMetalsAmount>92.18149</baseMetalsAmount>
          <preciousMetalsAmount>0</preciousMetalsAmount>
          <foodAvailability>0</foodAvailability>
        </Planet_Class>
        <Planet_Class>
          <planetName>Alpho II</planetName>
          <biome>Toxic (Sulphur)</biome>
          <biomeID>18</biomeID>
          <inhabited>false</inhabited>
          <population>0</population>
          <size>86</size>
          <usableSpace>0.6691121</usableSpace>
          <baseMetalsAmount>98.98859</baseMetalsAmount>
          <preciousMetalsAmount>48.41492</preciousMetalsAmount>
          <foodAvailability>0</foodAvailability>
        </Planet_Class>
        <Planet_Class>
          <planetName>Alpho III</planetName>
          <biome>Gas Giant Helium</biome>
          <biomeID>7</biomeID>
          <inhabited>false</inhabited>
          <population>9897751</population>
          <size>63</size>
          <usableSpace>0</usableSpace>
          <baseMetalsAmount>0</baseMetalsAmount>
          <preciousMetalsAmount>0</preciousMetalsAmount>
          <foodAvailability>0</foodAvailability>
        </Planet_Class>
        <Planet_Class>
          <planetName>Alpho IV</planetName>
          <biome>Ocean</biome>
          <biomeID>0</biomeID>
          <inhabited>false</inhabited>
          <population>969182976</population>
          <size>83</size>
          <usableSpace>0.3829204</usableSpace>
          <baseMetalsAmount>56.2824974</baseMetalsAmount>
          <preciousMetalsAmount>49.5758</preciousMetalsAmount>
          <foodAvailability>59.2978</foodAvailability>
        </Planet_Class>
      </Array>
    </System_Class>
    <System_Class>
      <systemName>Korus</systemName>
      <colour>Pink</colour>
      <allegiance>0</allegiance>
      <posX>2310</posX>
      <posZ>9577</posZ>
      <nPlanets>4</nPlanets>
      <Array>
        <Planet_Class>
          <planetName>Korus I</planetName>
          <biome>Gas Giant Hydrogen</biome>
          <biomeID>8</biomeID>
          <inhabited>false</inhabited>
          <population>2413094</population>
          <size>71</size>
          <usableSpace>0</usableSpace>
          <baseMetalsAmount>0</baseMetalsAmount>
          <preciousMetalsAmount>0</preciousMetalsAmount>
          <foodAvailability>0</foodAvailability>
        </Planet_Class>
        <Planet_Class>
          <planetName>Korus II</planetName>
          <biome>Ocean</biome>
          <biomeID>0</biomeID>
          <inhabited>false</inhabited>
          <population>425262272</population>
          <size>68</size>
          <usableSpace>0.22706306</usableSpace>
          <baseMetalsAmount>49.95535</baseMetalsAmount>
          <preciousMetalsAmount>42.9671364</preciousMetalsAmount>
          <foodAvailability>26.5154324</foodAvailability>
        </Planet_Class>
        <Planet_Class>
          <planetName>Korus III</planetName>
          <biome>Toxic (Phosphor)</biome>
          <biomeID>17</biomeID>
          <inhabited>false</inhabited>
          <population>0</population>
          <size>94</size>
          <usableSpace>0.36834234</usableSpace>
          <baseMetalsAmount>32.58419</baseMetalsAmount>
          <preciousMetalsAmount>42.63439</preciousMetalsAmount>
          <foodAvailability>0</foodAvailability>
        </Planet_Class>
        <Planet_Class>
          <planetName>Korus IV</planetName>
          <biome>Glass World</biome>
          <biomeID>0</biomeID>
          <inhabited>false</inhabited>
          <population>551276416</population>
          <size>84</size>
          <usableSpace>0.465446383</usableSpace>
          <baseMetalsAmount>26.4398422</baseMetalsAmount>
          <preciousMetalsAmount>46.62816</preciousMetalsAmount>
          <foodAvailability>99.18826</foodAvailability>
        </Planet_Class>
      </Array>
    </System_Class>
    <System_Class>
      <systemName>Alpho</systemName>
      <colour>Blue</colour>
      <allegiance>0</allegiance>
      <posX>4576</posX>
      <posZ>-6611</posZ>
      <nPlanets>5</nPlanets>
      <Array>
        <Planet_Class>
          <planetName>Alpho I</planetName>
          <biome>Swamp</biome>
          <biomeID>0</biomeID>
          <inhabited>false</inhabited>
          <population>787449536</population>
          <size>81</size>
          <usableSpace>0.102365069</usableSpace>
          <baseMetalsAmount>50.09951</baseMetalsAmount>
          <preciousMetalsAmount>146.077972</preciousMetalsAmount>
          <foodAvailability>49.5362854</foodAvailability>
        </Planet_Class>
        <Planet_Class>
          <planetName>Alpho II</planetName>
          <biome>Gas Giant Helium</biome>
          <biomeID>7</biomeID>
          <inhabited>false</inhabited>
          <population>0</population>
          <size>70</size>
          <usableSpace>0</usableSpace>
          <baseMetalsAmount>0</baseMetalsAmount>
          <preciousMetalsAmount>0</preciousMetalsAmount>
          <foodAvailability>0</foodAvailability>
        </Planet_Class>
        <Planet_Class>
          <planetName>Alpho III</planetName>
          <biome>Glass World</biome>
          <biomeID>0</biomeID>
          <inhabited>false</inhabited>
          <population>0</population>
          <size>60</size>
          <usableSpace>0.142993644</usableSpace>
          <baseMetalsAmount>3.51594162</baseMetalsAmount>
          <preciousMetalsAmount>50.72295</preciousMetalsAmount>
          <foodAvailability>42.6622238</foodAvailability>
        </Planet_Class>
        <Planet_Class>
          <planetName>Alpho IV</planetName>
          <biome>Arid</biome>
          <biomeID>0</biomeID>
          <inhabited>false</inhabited>
          <population>0</population>
          <size>51</size>
          <usableSpace>0.319375217</usableSpace>
          <baseMetalsAmount>49.5007362</baseMetalsAmount>
          <preciousMetalsAmount>51.668026</preciousMetalsAmount>
          <foodAvailability>43.37235</foodAvailability>
        </Planet_Class>
        <Planet_Class>
          <planetName>Alpho V</planetName>
          <biome>Gas Giant Helium</biome>
          <biomeID>7</biomeID>
          <inhabited>false</inhabited>
          <population>2397410</population>
          <size>88</size>
          <usableSpace>0</usableSpace>
          <baseMetalsAmount>0</baseMetalsAmount>
          <preciousMetalsAmount>0</preciousMetalsAmount>
          <foodAvailability>0</foodAvailability>
        </Planet_Class>
      </Array>
    </System_Class>
    <System_Class>
      <systemName>Traous</systemName>
      <colour>Green_Light</colour>
      <allegiance>0</allegiance>
      <posX>-3325</posX>
      <posZ>-4316</posZ>
      <nPlanets>5</nPlanets>
      <Array>
        <Planet_Class>
          <planetName>Traous I</planetName>
          <biome>Toxic (Phosphor)</biome>
          <biomeID>17</biomeID>
          <inhabited>false</inhabited>
          <population>4997948</population>
          <size>58</size>
          <usableSpace>0.647330463</usableSpace>
          <baseMetalsAmount>49.065773</baseMetalsAmount>
          <preciousMetalsAmount>50.6688843</preciousMetalsAmount>
          <foodAvailability>0</foodAvailability>
        </Planet_Class>
        <Planet_Class>
          <planetName>Traous II</planetName>
          <biome>Desert</biome>
          <biomeID>0</biomeID>
          <inhabited>false</inhabited>
          <population>0</population>
          <size>90</size>
          <usableSpace>0.484562</usableSpace>
          <baseMetalsAmount>50.1994972</baseMetalsAmount>
          <preciousMetalsAmount>50.422287</preciousMetalsAmount>
          <foodAvailability>60.6857758</foodAvailability>
        </Planet_Class>
        <Planet_Class>
          <planetName>Traous III</planetName>
          <biome>Tropical</biome>
          <biomeID>0</biomeID>
          <inhabited>false</inhabited>
          <population>0</population>
          <size>77</size>
          <usableSpace>0.206679955</usableSpace>
          <baseMetalsAmount>67.7933655</baseMetalsAmount>
          <preciousMetalsAmount>55.80816</preciousMetalsAmount>
          <foodAvailability>49.4093</foodAvailability>
        </Planet_Class>
        <Planet_Class>
          <planetName>Traous IV</planetName>
          <biome>Gas Giant Hydrogen</biome>
          <biomeID>8</biomeID>
          <inhabited>false</inhabited>
          <population>6444359</population>
          <size>62</size>
          <usableSpace>0</usableSpace>
          <baseMetalsAmount>0</baseMetalsAmount>
          <preciousMetalsAmount>0</preciousMetalsAmount>
          <foodAvailability>0</foodAvailability>
        </Planet_Class>
        <Planet_Class>
          <planetName>Traous V</planetName>
          <biome>Toxic (Phosphor)</biome>
          <biomeID>17</biomeID>
          <inhabited>false</inhabited>
          <population>0</population>
          <size>54</size>
          <usableSpace>0.4766747</usableSpace>
          <baseMetalsAmount>53.4007835</baseMetalsAmount>
          <preciousMetalsAmount>53.08084</preciousMetalsAmount>
          <foodAvailability>0</foodAvailability>
        </Planet_Class>
      </Array>
    </System_Class>
    <System_Class>
      <systemName>Durack</systemName>
      <colour>Blue</colour>
      <allegiance>0</allegiance>
      <posX>-5212</posX>
      <posZ>1717</posZ>
      <nPlanets>6</nPlanets>
      <Array>
        <Planet_Class>
          <planetName>Durack I</planetName>
          <biome>Glacial</biome>
          <biomeID>0</biomeID>
          <inhabited>false</inhabited>
          <population>793476160</population>
          <size>60</size>
          <usableSpace>0.113991886</usableSpace>
          <baseMetalsAmount>49.1162338</baseMetalsAmount>
          <preciousMetalsAmount>50.1281433</preciousMetalsAmount>
          <foodAvailability>64.4388657</foodAvailability>
        </Planet_Class>
        <Planet_Class>
          <planetName>Durack II</planetName>
          <biome>Asteroid</biome>
          <biomeID>3</biomeID>
          <inhabited>false</inhabited>
          <population>8438328</population>
          <size>62</size>
          <usableSpace>0.241852373</usableSpace>
          <baseMetalsAmount>0</baseMetalsAmount>
          <preciousMetalsAmount>0</preciousMetalsAmount>
          <foodAvailability>0</foodAvailability>
        </Planet_Class>
        <Planet_Class>
          <planetName>Durack III</planetName>
          <biome>Barren</biome>
          <biomeID>4</biomeID>
          <inhabited>false</inhabited>
          <population>9097726</population>
          <size>76</size>
          <usableSpace>0.615330935</usableSpace>
          <baseMetalsAmount>65.04864</baseMetalsAmount>
          <preciousMetalsAmount>51.06005</preciousMetalsAmount>
          <foodAvailability>0</foodAvailability>
        </Planet_Class>
        <Planet_Class>
          <planetName>Durack IV</planetName>
          <biome>Tundra</biome>
          <biomeID>0</biomeID>
          <inhabited>false</inhabited>
          <population>119122304</population>
          <size>78</size>
          <usableSpace>0.5623833</usableSpace>
          <baseMetalsAmount>46.2423439</baseMetalsAmount>
          <preciousMetalsAmount>49.7966423</preciousMetalsAmount>
          <foodAvailability>61.69281</foodAvailability>
        </Planet_Class>
        <Planet_Class>
          <planetName>Durack V</planetName>
          <biome>Swamp</biome>
          <biomeID>0</biomeID>
          <inhabited>false</inhabited>
          <population>720696128</population>
          <size>62</size>
          <usableSpace>0.143915057</usableSpace>
          <baseMetalsAmount>24.0982151</baseMetalsAmount>
          <preciousMetalsAmount>51.325325</preciousMetalsAmount>
          <foodAvailability>45.53458</foodAvailability>
        </Planet_Class>
        <Planet_Class>
          <planetName>Durack VI</planetName>
          <biome>Gas Giant Helium</biome>
          <biomeID>7</biomeID>
          <inhabited>false</inhabited>
          <population>0</population>
          <size>56</size>
          <usableSpace>0</usableSpace>
          <baseMetalsAmount>0</baseMetalsAmount>
          <preciousMetalsAmount>0</preciousMetalsAmount>
          <foodAvailability>0</foodAvailability>
        </Planet_Class>
      </Array>
    </System_Class>
    <System_Class>
      <systemName>Othorix</systemName>
      <colour>Pink</colour>
      <allegiance>0</allegiance>
      <posX>-6088</posX>
      <posZ>-1319</posZ>
      <nPlanets>5</nPlanets>
      <Array>
        <Planet_Class>
          <planetName>Othorix I</planetName>
          <biome>Desert</biome>
          <biomeID>0</biomeID>
          <inhabited>false</inhabited>
          <population>757759168</population>
          <size>50</size>
          <usableSpace>0.4867291</usableSpace>
          <baseMetalsAmount>50.543457</baseMetalsAmount>
          <preciousMetalsAmount>45.2333374</preciousMetalsAmount>
          <foodAvailability>54.338707</foodAvailability>
        </Planet_Class>
        <Planet_Class>
          <planetName>Othorix II</planetName>
          <biome>Glacial</biome>
          <biomeID>0</biomeID>
          <inhabited>false</inhabited>
          <population>2249818</population>
          <size>57</size>
          <usableSpace>0.210699439</usableSpace>
          <baseMetalsAmount>54.6717224</baseMetalsAmount>
          <preciousMetalsAmount>50.3915062</preciousMetalsAmount>
          <foodAvailability>37.3999252</foodAvailability>
        </Planet_Class>
        <Planet_Class>
          <planetName>Othorix III</planetName>
          <biome>Molten</biome>
          <biomeID>12</biomeID>
          <inhabited>false</inhabited>
          <population>257952</population>
          <size>70</size>
          <usableSpace>0.238790676</usableSpace>
          <baseMetalsAmount>42.14332</baseMetalsAmount>
          <preciousMetalsAmount>45.64968</preciousMetalsAmount>
          <foodAvailability>0</foodAvailability>
        </Planet_Class>
        <Planet_Class>
          <planetName>Othorix IV</planetName>
          <biome>Glacial</biome>
          <biomeID>0</biomeID>
          <inhabited>false</inhabited>
          <population>0</population>
          <size>98</size>
          <usableSpace>0.15380612</usableSpace>
          <baseMetalsAmount>53.92775</baseMetalsAmount>
          <preciousMetalsAmount>26.030735</preciousMetalsAmount>
          <foodAvailability>35.0758743</foodAvailability>
        </Planet_Class>
        <Planet_Class>
          <planetName>Othorix V</planetName>
          <biome>Desert</biome>
          <biomeID>0</biomeID>
          <inhabited>false</inhabited>
          <population>739657344</population>
          <size>69</size>
          <usableSpace>0.721402049</usableSpace>
          <baseMetalsAmount>51.5417671</baseMetalsAmount>
          <preciousMetalsAmount>6.40052032</preciousMetalsAmount>
          <foodAvailability>67.23985</foodAvailability>
        </Planet_Class>
      </Array>
    </System_Class>
    <System_Class>
      <systemName>Dendo</systemName>
      <colour>Pink</colour>
      <allegiance>3</allegiance>
      <posX>5626</posX>
      <posZ>7436</posZ>
      <nPlanets>3</nPlanets>
      <Array>
        <Planet_Class>
          <planetName>Dendo I</planetName>
          <biome>Continental</biome>
          <biomeID>0</biomeID>
          <inhabited>false</inhabited>
          <population>801413184</population>
          <size>64</size>
          <usableSpace>0.4794307</usableSpace>
          <baseMetalsAmount>0</baseMetalsAmount>
          <preciousMetalsAmount>29.0105247</preciousMetalsAmount>
          <foodAvailability>59.9145241</foodAvailability>
        </Planet_Class>
        <Planet_Class>
          <planetName>Dendo II</planetName>
          <biome>Moon</biome>
          <biomeID>13</biomeID>
          <inhabited>false</inhabited>
          <population>0</population>
          <size>72</size>
          <usableSpace>0.348914623</usableSpace>
          <baseMetalsAmount>0</baseMetalsAmount>
          <preciousMetalsAmount>0</preciousMetalsAmount>
          <foodAvailability>0</foodAvailability>
        </Planet_Class>
        <Planet_Class>
          <planetName>Dendo III</planetName>
          <biome>Moon</biome>
          <biomeID>13</biomeID>
          <inhabited>false</inhabited>
          <population>0</population>
          <size>59</size>
          <usableSpace>0.606514335</usableSpace>
          <baseMetalsAmount>0</baseMetalsAmount>
          <preciousMetalsAmount>0</preciousMetalsAmount>
          <foodAvailability>0</foodAvailability>
        </Planet_Class>
      </Array>
    </System_Class>
    <System_Class>
      <systemName>Othorix</systemName>
      <colour>White</colour>
      <allegiance>1</allegiance>
      <posX>393</posX>
      <posZ>-3962</posZ>
      <nPlanets>6</nPlanets>
      <Array>
        <Planet_Class>
          <planetName>Othorix I</planetName>
          <biome>Asteroid</biome>
          <biomeID>3</biomeID>
          <inhabited>false</inhabited>
          <population>6815670</population>
          <size>80</size>
          <usableSpace>0.479250222</usableSpace>
          <baseMetalsAmount>0</baseMetalsAmount>
          <preciousMetalsAmount>0</preciousMetalsAmount>
          <foodAvailability>0</foodAvailability>
        </Planet_Class>
        <Planet_Class>
          <planetName>Othorix II</planetName>
          <biome>Tundra</biome>
          <biomeID>0</biomeID>
          <inhabited>false</inhabited>
          <population>374721376</population>
          <size>79</size>
          <usableSpace>0.62527746</usableSpace>
          <baseMetalsAmount>47.1426926</baseMetalsAmount>
          <preciousMetalsAmount>49.0247</preciousMetalsAmount>
          <foodAvailability>46.6244736</foodAvailability>
        </Planet_Class>
        <Planet_Class>
          <planetName>Othorix III</planetName>
          <biome>Gas Giant Helium</biome>
          <biomeID>7</biomeID>
          <inhabited>false</inhabited>
          <population>0</population>
          <size>82</size>
          <usableSpace>0</usableSpace>
          <baseMetalsAmount>0</baseMetalsAmount>
          <preciousMetalsAmount>0</preciousMetalsAmount>
          <foodAvailability>0</foodAvailability>
        </Planet_Class>
        <Planet_Class>
          <planetName>Othorix IV</planetName>
          <biome>Ocean</biome>
          <biomeID>0</biomeID>
          <inhabited>false</inhabited>
          <population>0</population>
          <size>89</size>
          <usableSpace>0.231343612</usableSpace>
          <baseMetalsAmount>50.9285774</baseMetalsAmount>
          <preciousMetalsAmount>32.17624</preciousMetalsAmount>
          <foodAvailability>58.0825958</foodAvailability>
        </Planet_Class>
        <Planet_Class>
          <planetName>Othorix V</planetName>
          <biome>Gas Giant Helium</biome>
          <biomeID>7</biomeID>
          <inhabited>false</inhabited>
          <population>3942645</population>
          <size>66</size>
          <usableSpace>0</usableSpace>
          <baseMetalsAmount>0</baseMetalsAmount>
          <preciousMetalsAmount>0</preciousMetalsAmount>
          <foodAvailability>0</foodAvailability>
        </Planet_Class>
        <Planet_Class>
          <planetName>Othorix VI</planetName>
          <biome>Oasis</biome>
          <biomeID>0</biomeID>
          <inhabited>false</inhabited>
          <population>753642304</population>
          <size>68</size>
          <usableSpace>0.687056</usableSpace>
          <baseMetalsAmount>49.48291</baseMetalsAmount>
          <preciousMetalsAmount>65.5801</preciousMetalsAmount>
          <foodAvailability>46.14613</foodAvailability>
        </Planet_Class>
      </Array>
    </System_Class>
    <System_Class>
      <systemName>Traous</systemName>
      <colour>Orange</colour>
      <allegiance>0</allegiance>
      <posX>-9963</posX>
      <posZ>-541</posZ>
      <nPlanets>1</nPlanets>
      <Array>
        <Planet_Class>
          <planetName>Traous I</planetName>
          <biome>Continental</biome>
          <biomeID>0</biomeID>
          <inhabited>false</inhabited>
          <population>615884864</population>
          <size>53</size>
          <usableSpace>0.5554131</usableSpace>
          <baseMetalsAmount>19.3579884</baseMetalsAmount>
          <preciousMetalsAmount>52.53945</preciousMetalsAmount>
          <foodAvailability>40.9590225</foodAvailability>
        </Planet_Class>
      </Array>
    </System_Class>
    <System_Class>
      <systemName>Pretentis</systemName>
      <colour>White</colour>
      <allegiance>3</allegiance>
      <posX>8706</posX>
      <posZ>-470</posZ>
      <nPlanets>3</nPlanets>
      <Array>
        <Planet_Class>
          <planetName>Pretentis I</planetName>
          <biome>Glass World</biome>
          <biomeID>0</biomeID>
          <inhabited>false</inhabited>
          <population>380511648</population>
          <size>60</size>
          <usableSpace>0.127401173</usableSpace>
          <baseMetalsAmount>34.1898537</baseMetalsAmount>
          <preciousMetalsAmount>47.65674</preciousMetalsAmount>
          <foodAvailability>51.60929</foodAvailability>
        </Planet_Class>
        <Planet_Class>
          <planetName>Pretentis II</planetName>
          <biome>Continental</biome>
          <biomeID>0</biomeID>
          <inhabited>false</inhabited>
          <population>491537088</population>
          <size>60</size>
          <usableSpace>0.409814477</usableSpace>
          <baseMetalsAmount>43.84354</baseMetalsAmount>
          <preciousMetalsAmount>75.56138</preciousMetalsAmount>
          <foodAvailability>44.06677</foodAvailability>
        </Planet_Class>
        <Planet_Class>
          <planetName>Pretentis III</planetName>
          <biome>Toxic (Sulphur)</biome>
          <biomeID>18</biomeID>
          <inhabited>false</inhabited>
          <population>0</population>
          <size>58</size>
          <usableSpace>0.379023671</usableSpace>
          <baseMetalsAmount>57.4186478</baseMetalsAmount>
          <preciousMetalsAmount>105.991959</preciousMetalsAmount>
          <foodAvailability>0</foodAvailability>
        </Planet_Class>
      </Array>
    </System_Class>
    <System_Class>
      <systemName>Erzaf</systemName>
      <colour>Red</colour>
      <allegiance>0</allegiance>
      <posX>-1940</posX>
      <posZ>-7327</posZ>
      <nPlanets>3</nPlanets>
      <Array>
        <Planet_Class>
          <planetName>Erzaf I</planetName>
          <biome>Glacial</biome>
          <biomeID>0</biomeID>
          <inhabited>false</inhabited>
          <population>398125504</population>
          <size>69</size>
          <usableSpace>0.1443226</usableSpace>
          <baseMetalsAmount>67.6331</baseMetalsAmount>
          <preciousMetalsAmount>70.38557</preciousMetalsAmount>
          <foodAvailability>62.5798149</foodAvailability>
        </Planet_Class>
        <Planet_Class>
          <planetName>Erzaf II</planetName>
          <biome>Gas Giant Helium</biome>
          <biomeID>7</biomeID>
          <inhabited>false</inhabited>
          <population>0</population>
          <size>71</size>
          <usableSpace>0</usableSpace>
          <baseMetalsAmount>0</baseMetalsAmount>
          <preciousMetalsAmount>0</preciousMetalsAmount>
          <foodAvailability>0</foodAvailability>
        </Planet_Class>
        <Planet_Class>
          <planetName>Erzaf III</planetName>
          <biome>Molten</biome>
          <biomeID>12</biomeID>
          <inhabited>false</inhabited>
          <population>4714639</population>
          <size>96</size>
          <usableSpace>0.3825064</usableSpace>
          <baseMetalsAmount>52.85941</baseMetalsAmount>
          <preciousMetalsAmount>44.129837</preciousMetalsAmount>
          <foodAvailability>0</foodAvailability>
        </Planet_Class>
      </Array>
    </System_Class>
    <System_Class>
      <systemName>Urnin</systemName>
      <colour>Green</colour>
      <allegiance>0</allegiance>
      <posX>1810</posX>
      <posZ>5208</posZ>
      <nPlanets>1</nPlanets>
      <Array>
        <Planet_Class>
          <planetName>Urnin I</planetName>
          <biome>Glacial</biome>
          <biomeID>0</biomeID>
          <inhabited>false</inhabited>
          <population>321782432</population>
          <size>83</size>
          <usableSpace>0.207260028</usableSpace>
          <baseMetalsAmount>53.7431946</baseMetalsAmount>
          <preciousMetalsAmount>52.2042542</preciousMetalsAmount>
          <foodAvailability>132.011368</foodAvailability>
        </Planet_Class>
      </Array>
    </System_Class>
    <System_Class>
      <systemName>Dendo</systemName>
      <colour>Green_Light</colour>
      <allegiance>0</allegiance>
      <posX>5058</posX>
      <posZ>-2116</posZ>
      <nPlanets>7</nPlanets>
      <Array>
        <Planet_Class>
          <planetName>Dendo I</planetName>
          <biome>Swamp</biome>
          <biomeID>0</biomeID>
          <inhabited>false</inhabited>
          <population>494450048</population>
          <size>90</size>
          <usableSpace>0.2921091</usableSpace>
          <baseMetalsAmount>51.587326</baseMetalsAmount>
          <preciousMetalsAmount>56.58744</preciousMetalsAmount>
          <foodAvailability>49.9363365</foodAvailability>
        </Planet_Class>
        <Planet_Class>
          <planetName>Dendo II</planetName>
          <biome>Arid</biome>
          <biomeID>0</biomeID>
          <inhabited>false</inhabited>
          <population>663485568</population>
          <size>78</size>
          <usableSpace>0.185190022</usableSpace>
          <baseMetalsAmount>0</baseMetalsAmount>
          <preciousMetalsAmount>47.2558</preciousMetalsAmount>
          <foodAvailability>50.4990959</foodAvailability>
        </Planet_Class>
        <Planet_Class>
          <planetName>Dendo III</planetName>
          <biome>Arctic</biome>
          <biomeID>0</biomeID>
          <inhabited>false</inhabited>
          <population>0</population>
          <size>81</size>
          <usableSpace>0.6384407</usableSpace>
          <baseMetalsAmount>49.796093</baseMetalsAmount>
          <preciousMetalsAmount>78.28127</preciousMetalsAmount>
          <foodAvailability>59.0861778</foodAvailability>
        </Planet_Class>
        <Planet_Class>
          <planetName>Dendo IV</planetName>
          <biome>Tropical</biome>
          <biomeID>0</biomeID>
          <inhabited>false</inhabited>
          <population>0</population>
          <size>78</size>
          <usableSpace>0.5920947</usableSpace>
          <baseMetalsAmount>53.59178</baseMetalsAmount>
          <preciousMetalsAmount>56.500824</preciousMetalsAmount>
          <foodAvailability>59.57677</foodAvailability>
        </Planet_Class>
        <Planet_Class>
          <planetName>Dendo V</planetName>
          <biome>Arctic</biome>
          <biomeID>0</biomeID>
          <inhabited>false</inhabited>
          <population>742830656</population>
          <size>69</size>
          <usableSpace>0.472378254</usableSpace>
          <baseMetalsAmount>37.17691</baseMetalsAmount>
          <preciousMetalsAmount>40.90909</preciousMetalsAmount>
          <foodAvailability>49.4366379</foodAvailability>
        </Planet_Class>
        <Planet_Class>
          <planetName>Dendo VI</planetName>
          <biome>Oasis</biome>
          <biomeID>0</biomeID>
          <inhabited>false</inhabited>
          <population>613199936</population>
          <size>64</size>
          <usableSpace>0.5218528</usableSpace>
          <baseMetalsAmount>30.8196983</baseMetalsAmount>
          <preciousMetalsAmount>1.74659348</preciousMetalsAmount>
          <foodAvailability>86.6577759</foodAvailability>
        </Planet_Class>
        <Planet_Class>
          <planetName>Dendo VII</planetName>
          <biome>Molten</biome>
          <biomeID>12</biomeID>
          <inhabited>false</inhabited>
          <population>3017032</population>
          <size>61</size>
          <usableSpace>0.303293943</usableSpace>
          <baseMetalsAmount>7.15325546</baseMetalsAmount>
          <preciousMetalsAmount>50.3251152</preciousMetalsAmount>
          <foodAvailability>0</foodAvailability>
        </Planet_Class>
      </Array>
    </System_Class>
    <System_Class>
      <systemName>Urnin</systemName>
      <colour>White</colour>
      <allegiance>0</allegiance>
      <posX>-3705</posX>
      <posZ>6857</posZ>
      <nPlanets>6</nPlanets>
      <Array>
        <Planet_Class>
          <planetName>Urnin I</planetName>
          <biome>Gas Giant Helium</biome>
          <biomeID>7</biomeID>
          <inhabited>false</inhabited>
          <population>5177497</population>
          <size>62</size>
          <usableSpace>0</usableSpace>
          <baseMetalsAmount>0</baseMetalsAmount>
          <preciousMetalsAmount>0</preciousMetalsAmount>
          <foodAvailability>0</foodAvailability>
        </Planet_Class>
        <Planet_Class>
          <planetName>Urnin II</planetName>
          <biome>Mediterranean</biome>
          <biomeID>0</biomeID>
          <inhabited>false</inhabited>
          <population>0</population>
          <size>77</size>
          <usableSpace>0.598842442</usableSpace>
          <baseMetalsAmount>104.320816</baseMetalsAmount>
          <preciousMetalsAmount>46.21875</preciousMetalsAmount>
          <foodAvailability>49.162838</foodAvailability>
        </Planet_Class>
        <Planet_Class>
          <planetName>Urnin III</planetName>
          <biome>Arid</biome>
          <biomeID>0</biomeID>
          <inhabited>false</inhabited>
          <population>0</population>
          <size>51</size>
          <usableSpace>0.391613632</usableSpace>
          <baseMetalsAmount>48.1159821</baseMetalsAmount>
          <preciousMetalsAmount>98.08508</preciousMetalsAmount>
          <foodAvailability>50.645565</foodAvailability>
        </Planet_Class>
        <Planet_Class>
          <planetName>Urnin IV</planetName>
          <biome>Barren</biome>
          <biomeID>4</biomeID>
          <inhabited>false</inhabited>
          <population>4670893</population>
          <size>96</size>
          <usableSpace>0.895195365</usableSpace>
          <baseMetalsAmount>50.9435959</baseMetalsAmount>
          <preciousMetalsAmount>97.1762848</preciousMetalsAmount>
          <foodAvailability>0</foodAvailability>
        </Planet_Class>
        <Planet_Class>
          <planetName>Urnin V</planetName>
          <biome>Toxic (Sulphur)</biome>
          <biomeID>18</biomeID>
          <inhabited>false</inhabited>
          <population>7727857</population>
          <size>71</size>
          <usableSpace>0.291277468</usableSpace>
          <baseMetalsAmount>61.92664</baseMetalsAmount>
          <preciousMetalsAmount>50.4349174</preciousMetalsAmount>
          <foodAvailability>0</foodAvailability>
        </Planet_Class>
        <Planet_Class>
          <planetName>Urnin VI</planetName>
          <biome>Toxic (Phosphor)</biome>
          <biomeID>17</biomeID>
          <inhabited>false</inhabited>
          <population>3621265</population>
          <size>86</size>
          <usableSpace>0.5409321</usableSpace>
          <baseMetalsAmount>43.0914421</baseMetalsAmount>
          <preciousMetalsAmount>65.7289</preciousMetalsAmount>
          <foodAvailability>0</foodAvailability>
        </Planet_Class>
      </Array>
    </System_Class>
    <System_Class>
      <systemName>Korus</systemName>
      <colour>Green_Light</colour>
      <allegiance>3</allegiance>
      <posX>-9901</posX>
      <posZ>-3727</posZ>
      <nPlanets>3</nPlanets>
      <Array>
        <Planet_Class>
          <planetName>Korus I</planetName>
          <biome>Molten</biome>
          <biomeID>12</biomeID>
          <inhabited>false</inhabited>
          <population>8239343</population>
          <size>62</size>
          <usableSpace>0.4981196</usableSpace>
          <baseMetalsAmount>53.1198463</baseMetalsAmount>
          <preciousMetalsAmount>49.30455</preciousMetalsAmount>
          <foodAvailability>0</foodAvailability>
        </Planet_Class>
        <Planet_Class>
          <planetName>Korus II</planetName>
          <biome>Arid</biome>
          <biomeID>0</biomeID>
          <inhabited>false</inhabited>
          <population>0</population>
          <size>53</size>
          <usableSpace>0.294244736</usableSpace>
          <baseMetalsAmount>40.2981148</baseMetalsAmount>
          <preciousMetalsAmount>54.367897</preciousMetalsAmount>
          <foodAvailability>50.641674</foodAvailability>
        </Planet_Class>
        <Planet_Class>
          <planetName>Korus III</planetName>
          <biome>Mediterranean</biome>
          <biomeID>0</biomeID>
          <inhabited>false</inhabited>
          <population>0</population>
          <size>79</size>
          <usableSpace>0.258657873</usableSpace>
          <baseMetalsAmount>54.98031</baseMetalsAmount>
          <preciousMetalsAmount>0</preciousMetalsAmount>
          <foodAvailability>49.245388</foodAvailability>
        </Planet_Class>
      </Array>
    </System_Class>
    <System_Class>
      <systemName>Korus</systemName>
      <colour>Red</colour>
      <allegiance>1</allegiance>
      <posX>9651</posX>
      <posZ>3517</posZ>
      <nPlanets>6</nPlanets>
      <Array>
        <Planet_Class>
          <planetName>Korus I</planetName>
          <biome>Tropical</biome>
          <biomeID>0</biomeID>
          <inhabited>false</inhabited>
          <population>521304352</population>
          <size>71</size>
          <usableSpace>0.5889612</usableSpace>
          <baseMetalsAmount>67.99014</baseMetalsAmount>
          <preciousMetalsAmount>50.2091</preciousMetalsAmount>
          <foodAvailability>40.4157524</foodAvailability>
        </Planet_Class>
        <Planet_Class>
          <planetName>Korus II</planetName>
          <biome>Oasis</biome>
          <biomeID>0</biomeID>
          <inhabited>false</inhabited>
          <population>357091264</population>
          <size>66</size>
          <usableSpace>0.443424255</usableSpace>
          <baseMetalsAmount>68.50713</baseMetalsAmount>
          <preciousMetalsAmount>46.77579</preciousMetalsAmount>
          <foodAvailability>56.49611</foodAvailability>
        </Planet_Class>
        <Planet_Class>
          <planetName>Korus III</planetName>
          <biome>Ocean</biome>
          <biomeID>0</biomeID>
          <inhabited>false</inhabited>
          <population>256732624</population>
          <size>79</size>
          <usableSpace>0.140201524</usableSpace>
          <baseMetalsAmount>49.892498</baseMetalsAmount>
          <preciousMetalsAmount>54.3939323</preciousMetalsAmount>
          <foodAvailability>3.94582748</foodAvailability>
        </Planet_Class>
        <Planet_Class>
          <planetName>Korus IV</planetName>
          <biome>Toxic (Phosphor)</biome>
          <biomeID>17</biomeID>
          <inhabited>false</inhabited>
          <population>0</population>
          <size>71</size>
          <usableSpace>0.317037344</usableSpace>
          <baseMetalsAmount>49.11962</baseMetalsAmount>
          <preciousMetalsAmount>50.68135</preciousMetalsAmount>
          <foodAvailability>0</foodAvailability>
        </Planet_Class>
        <Planet_Class>
          <planetName>Korus V</planetName>
          <biome>Gas Giant Hydrogen</biome>
          <biomeID>8</biomeID>
          <inhabited>false</inhabited>
          <population>9325299</population>
          <size>61</size>
          <usableSpace>0</usableSpace>
          <baseMetalsAmount>0</baseMetalsAmount>
          <preciousMetalsAmount>0</preciousMetalsAmount>
          <foodAvailability>0</foodAvailability>
        </Planet_Class>
        <Planet_Class>
          <planetName>Korus VI</planetName>
          <biome>Glacial</biome>
          <biomeID>0</biomeID>
          <inhabited>false</inhabited>
          <population>0</population>
          <size>87</size>
          <usableSpace>0.2931746</usableSpace>
          <baseMetalsAmount>86.13962</baseMetalsAmount>
          <preciousMetalsAmount>49.0262871</preciousMetalsAmount>
          <foodAvailability>49.6692772</foodAvailability>
        </Planet_Class>
      </Array>
    </System_Class>
    <System_Class>
      <systemName>Korus</systemName>
      <colour>Green</colour>
      <allegiance>3</allegiance>
      <posX>-7355</posX>
      <posZ>8537</posZ>
      <nPlanets>7</nPlanets>
      <Array>
        <Planet_Class>
          <planetName>Korus I</planetName>
          <biome>Desert</biome>
          <biomeID>0</biomeID>
          <inhabited>false</inhabited>
          <population>72791496</population>
          <size>63</size>
          <usableSpace>0.7855605</usableSpace>
          <baseMetalsAmount>54.1331825</baseMetalsAmount>
          <preciousMetalsAmount>48.1091232</preciousMetalsAmount>
          <foodAvailability>53.04963</foodAvailability>
        </Planet_Class>
        <Planet_Class>
          <planetName>Korus II</planetName>
          <biome>Toxic (Sulphur)</biome>
          <biomeID>18</biomeID>
          <inhabited>false</inhabited>
          <population>6989644</population>
          <size>83</size>
          <usableSpace>0.208580032</usableSpace>
          <baseMetalsAmount>59.96255</baseMetalsAmount>
          <preciousMetalsAmount>38.08775</preciousMetalsAmount>
          <foodAvailability>0</foodAvailability>
        </Planet_Class>
        <Planet_Class>
          <planetName>Korus III</planetName>
          <biome>Oasis</biome>
          <biomeID>0</biomeID>
          <inhabited>false</inhabited>
          <population>0</population>
          <size>90</size>
          <usableSpace>0.203796819</usableSpace>
          <baseMetalsAmount>42.50907</baseMetalsAmount>
          <preciousMetalsAmount>50.61068</preciousMetalsAmount>
          <foodAvailability>52.11303</foodAvailability>
        </Planet_Class>
        <Planet_Class>
          <planetName>Korus IV</planetName>
          <biome>Oasis</biome>
          <biomeID>0</biomeID>
          <inhabited>false</inhabited>
          <population>0</population>
          <size>58</size>
          <usableSpace>0.321581</usableSpace>
          <baseMetalsAmount>50.755825</baseMetalsAmount>
          <preciousMetalsAmount>47.47469</preciousMetalsAmount>
          <foodAvailability>49.3463364</foodAvailability>
        </Planet_Class>
        <Planet_Class>
          <planetName>Korus V</planetName>
          <biome>Moon</biome>
          <biomeID>13</biomeID>
          <inhabited>false</inhabited>
          <population>9270336</population>
          <size>65</size>
          <usableSpace>0.7338642</usableSpace>
          <baseMetalsAmount>0</baseMetalsAmount>
          <preciousMetalsAmount>0</preciousMetalsAmount>
          <foodAvailability>0</foodAvailability>
        </Planet_Class>
        <Planet_Class>
          <planetName>Korus VI</planetName>
          <biome>Toxic (Sulphur)</biome>
          <biomeID>18</biomeID>
          <inhabited>false</inhabited>
          <population>9077849</population>
          <size>62</size>
          <usableSpace>0.3482561</usableSpace>
          <baseMetalsAmount>68.55905</baseMetalsAmount>
          <preciousMetalsAmount>59.6987839</preciousMetalsAmount>
          <foodAvailability>0</foodAvailability>
        </Planet_Class>
        <Planet_Class>
          <planetName>Korus VII</planetName>
          <biome>Gas Giant Hydrogen</biome>
          <biomeID>8</biomeID>
          <inhabited>false</inhabited>
          <population>2978960</population>
          <size>51</size>
          <usableSpace>0</usableSpace>
          <baseMetalsAmount>0</baseMetalsAmount>
          <preciousMetalsAmount>0</preciousMetalsAmount>
          <foodAvailability>0</foodAvailability>
        </Planet_Class>
      </Array>
    </System_Class>
    <System_Class>
      <systemName>Alpho</systemName>
      <colour>Blue</colour>
      <allegiance>0</allegiance>
      <posX>8881</posX>
      <posZ>-9666</posZ>
      <nPlanets>5</nPlanets>
      <Array>
        <Planet_Class>
          <planetName>Alpho I</planetName>
          <biome>Gas Giant Hydrogen</biome>
          <biomeID>8</biomeID>
          <inhabited>false</inhabited>
          <population>7589505</population>
          <size>81</size>
          <usableSpace>0</usableSpace>
          <baseMetalsAmount>0</baseMetalsAmount>
          <preciousMetalsAmount>0</preciousMetalsAmount>
          <foodAvailability>0</foodAvailability>
        </Planet_Class>
        <Planet_Class>
          <planetName>Alpho II</planetName>
          <biome>Gas Giant Hydrogen</biome>
          <biomeID>8</biomeID>
          <inhabited>false</inhabited>
          <population>2848336</population>
          <size>60</size>
          <usableSpace>0</usableSpace>
          <baseMetalsAmount>0</baseMetalsAmount>
          <preciousMetalsAmount>0</preciousMetalsAmount>
          <foodAvailability>0</foodAvailability>
        </Planet_Class>
        <Planet_Class>
          <planetName>Alpho III</planetName>
          <biome>Asteroid</biome>
          <biomeID>3</biomeID>
          <inhabited>false</inhabited>
          <population>0</population>
          <size>58</size>
          <usableSpace>0.497901261</usableSpace>
          <baseMetalsAmount>0</baseMetalsAmount>
          <preciousMetalsAmount>0</preciousMetalsAmount>
          <foodAvailability>0</foodAvailability>
        </Planet_Class>
        <Planet_Class>
          <planetName>Alpho IV</planetName>
          <biome>Desert</biome>
          <biomeID>0</biomeID>
          <inhabited>false</inhabited>
          <population>94788376</population>
          <size>55</size>
          <usableSpace>0.6469217</usableSpace>
          <baseMetalsAmount>58.1516876</baseMetalsAmount>
          <preciousMetalsAmount>40.35212</preciousMetalsAmount>
          <foodAvailability>47.5968742</foodAvailability>
        </Planet_Class>
        <Planet_Class>
          <planetName>Alpho V</planetName>
          <biome>Arctic</biome>
          <biomeID>0</biomeID>
          <inhabited>false</inhabited>
          <population>0</population>
          <size>99</size>
          <usableSpace>0.59109056</usableSpace>
          <baseMetalsAmount>5.03166962</baseMetalsAmount>
          <preciousMetalsAmount>44.37856</preciousMetalsAmount>
          <foodAvailability>47.2153244</foodAvailability>
        </Planet_Class>
      </Array>
    </System_Class>
    <System_Class>
      <systemName>Korus</systemName>
      <colour>Red</colour>
      <allegiance>1</allegiance>
      <posX>5435</posX>
      <posZ>-9513</posZ>
      <nPlanets>6</nPlanets>
      <Array>
        <Planet_Class>
          <planetName>Korus I</planetName>
          <biome>Glass World</biome>
          <biomeID>0</biomeID>
          <inhabited>false</inhabited>
          <population>578311680</population>
          <size>91</size>
          <usableSpace>0.136678785</usableSpace>
          <baseMetalsAmount>45.06124</baseMetalsAmount>
          <preciousMetalsAmount>53.1617279</preciousMetalsAmount>
          <foodAvailability>0</foodAvailability>
        </Planet_Class>
        <Planet_Class>
          <planetName>Korus II</planetName>
          <biome>Arctic</biome>
          <biomeID>0</biomeID>
          <inhabited>false</inhabited>
          <population>0</population>
          <size>68</size>
          <usableSpace>0.456644028</usableSpace>
          <baseMetalsAmount>69.5462</baseMetalsAmount>
          <preciousMetalsAmount>49.740303</preciousMetalsAmount>
          <foodAvailability>48.398243</foodAvailability>
        </Planet_Class>
        <Planet_Class>
          <planetName>Korus III</planetName>
          <biome>Moon</biome>
          <biomeID>13</biomeID>
          <inhabited>false</inhabited>
          <population>0</population>
          <size>68</size>
          <usableSpace>0.6210507</usableSpace>
          <baseMetalsAmount>0</baseMetalsAmount>
          <preciousMetalsAmount>0</preciousMetalsAmount>
          <foodAvailability>0</foodAvailability>
        </Planet_Class>
        <Planet_Class>
          <planetName>Korus IV</planetName>
          <biome>Gas Giant Methane</biome>
          <biomeID>9</biomeID>
          <inhabited>false</inhabited>
          <population>8903964</population>
          <size>96</size>
          <usableSpace>0</usableSpace>
          <baseMetalsAmount>0</baseMetalsAmount>
          <preciousMetalsAmount>0</preciousMetalsAmount>
          <foodAvailability>0</foodAvailability>
        </Planet_Class>
        <Planet_Class>
          <planetName>Korus V</planetName>
          <biome>Gas Giant Methane</biome>
          <biomeID>9</biomeID>
          <inhabited>false</inhabited>
          <population>7305144</population>
          <size>61</size>
          <usableSpace>0</usableSpace>
          <baseMetalsAmount>0</baseMetalsAmount>
          <preciousMetalsAmount>0</preciousMetalsAmount>
          <foodAvailability>0</foodAvailability>
        </Planet_Class>
        <Planet_Class>
          <planetName>Korus VI</planetName>
          <biome>Ocean</biome>
          <biomeID>0</biomeID>
          <inhabited>false</inhabited>
          <population>98579312</population>
          <size>74</size>
          <usableSpace>0.384547442</usableSpace>
          <baseMetalsAmount>47.2800255</baseMetalsAmount>
          <preciousMetalsAmount>47.0908165</preciousMetalsAmount>
          <foodAvailability>53.637516</foodAvailability>
        </Planet_Class>
      </Array>
    </System_Class>
    <System_Class>
      <systemName>Othorix</systemName>
      <colour>Red</colour>
      <allegiance>2</allegiance>
      <posX>-1789</posX>
      <posZ>9844</posZ>
      <nPlanets>3</nPlanets>
      <Array>
        <Planet_Class>
          <planetName>Othorix I</planetName>
          <biome>Barren</biome>
          <biomeID>4</biomeID>
          <inhabited>false</inhabited>
          <population>671178</population>
          <size>55</size>
          <usableSpace>0.8463489</usableSpace>
          <baseMetalsAmount>45.7886</baseMetalsAmount>
          <preciousMetalsAmount>54.06128</preciousMetalsAmount>
          <foodAvailability>0</foodAvailability>
        </Planet_Class>
        <Planet_Class>
          <planetName>Othorix II</planetName>
          <biome>Continental</biome>
          <biomeID>0</biomeID>
          <inhabited>false</inhabited>
          <population>72984776</population>
          <size>92</size>
          <usableSpace>0.643961</usableSpace>
          <baseMetalsAmount>40.4764023</baseMetalsAmount>
          <preciousMetalsAmount>54.66995</preciousMetalsAmount>
          <foodAvailability>35.2198334</foodAvailability>
        </Planet_Class>
        <Planet_Class>
          <planetName>Othorix III</planetName>
          <biome>Mediterranean</biome>
          <biomeID>0</biomeID>
          <inhabited>false</inhabited>
          <population>0</population>
          <size>76</size>
          <usableSpace>0.242947236</usableSpace>
          <baseMetalsAmount>50.7846222</baseMetalsAmount>
          <preciousMetalsAmount>34.3147125</preciousMetalsAmount>
          <foodAvailability>99.93039</foodAvailability>
        </Planet_Class>
      </Array>
    </System_Class>
    <System_Class>
      <systemName>Colosk</systemName>
      <colour>Green_Light</colour>
      <allegiance>0</allegiance>
      <posX>8257</posX>
      <posZ>9028</posZ>
      <nPlanets>2</nPlanets>
      <Array>
        <Planet_Class>
          <planetName>Colosk I</planetName>
          <biome>Toxic (Sulphur)</biome>
          <biomeID>18</biomeID>
          <inhabited>false</inhabited>
          <population>124633</population>
          <size>60</size>
          <usableSpace>0.4836183</usableSpace>
          <baseMetalsAmount>46.9871445</baseMetalsAmount>
          <preciousMetalsAmount>6.61829</preciousMetalsAmount>
          <foodAvailability>0</foodAvailability>
        </Planet_Class>
        <Planet_Class>
          <planetName>Colosk II</planetName>
          <biome>Asteroid</biome>
          <biomeID>3</biomeID>
          <inhabited>false</inhabited>
          <population>0</population>
          <size>63</size>
          <usableSpace>0.269923925</usableSpace>
          <baseMetalsAmount>0</baseMetalsAmount>
          <preciousMetalsAmount>0</preciousMetalsAmount>
          <foodAvailability>0</foodAvailability>
        </Planet_Class>
      </Array>
    </System_Class>
    <System_Class>
      <systemName>Traous</systemName>
      <colour>Green</colour>
      <allegiance>0</allegiance>
      <posX>7218</posX>
      <posZ>-5162</posZ>
      <nPlanets>3</nPlanets>
      <Array>
        <Planet_Class>
          <planetName>Traous I</planetName>
          <biome>Glass World</biome>
          <biomeID>0</biomeID>
          <inhabited>false</inhabited>
          <population>784020544</population>
          <size>79</size>
          <usableSpace>0.363262951</usableSpace>
          <baseMetalsAmount>64.40886</baseMetalsAmount>
          <preciousMetalsAmount>49.02689</preciousMetalsAmount>
          <foodAvailability>53.8290443</foodAvailability>
        </Planet_Class>
        <Planet_Class>
          <planetName>Traous II</planetName>
          <biome>Gas Giant Helium</biome>
          <biomeID>7</biomeID>
          <inhabited>false</inhabited>
          <population>0</population>
          <size>88</size>
          <usableSpace>0</usableSpace>
          <baseMetalsAmount>0</baseMetalsAmount>
          <preciousMetalsAmount>0</preciousMetalsAmount>
          <foodAvailability>0</foodAvailability>
        </Planet_Class>
        <Planet_Class>
          <planetName>Traous III</planetName>
          <biome>Oasis</biome>
          <biomeID>0</biomeID>
          <inhabited>false</inhabited>
          <population>247002592</population>
          <size>75</size>
          <usableSpace>0.233001187</usableSpace>
          <baseMetalsAmount>89.56447</baseMetalsAmount>
          <preciousMetalsAmount>50.71127</preciousMetalsAmount>
          <foodAvailability>55.4356537</foodAvailability>
        </Planet_Class>
      </Array>
    </System_Class>
  </systems>
  <generatedProduct>
    <height>20000</height>
    <width>20000</width>
    <numberofStars>100</numberofStars>
    <minimumPlanets>1</minimumPlanets>
    <maximumPlanets>7</maximumPlanets>
    <averagePlanetSize>50</averagePlanetSize>
    <habitableChance>50</habitableChance>
    <inhabitedChance>50</inhabitedChance>
    <resourceAbundancy>50</resourceAbundancy>
    <playerStrength>0</playerStrength>
    <toggledAI>
      <AI_Class>
        <race>
          <Species_Name>Orx</Species_Name>
          <Empire_Name>Orx Territory</Empire_Name>
          <Source>Core</Source>
        </race>
        <difficulty>0</difficulty>
        <startThreat>0</startThreat>
        <colour>
          <r>0.7924528</r>
          <g>0</g>
          <b>0</b>
          <a>1</a>
        </colour>
        <nPlanets>5</nPlanets>
      </AI_Class>
      <AI_Class>
        <race>
          <Species_Name>Ivorian</Species_Name>
          <Empire_Name>The Ivorian Empire</Empire_Name>
          <Source>Core</Source>
        </race>
        <difficulty>0</difficulty>
        <startThreat>0</startThreat>
        <colour>
          <r>0</r>
          <g>0.0254663154</g>
          <b>0.9150943</b>
          <a>1</a>
        </colour>
        <nPlanets>2</nPlanets>
      </AI_Class>
      <AI_Class>
        <race>
          <Species_Name>Enslavers</Species_Name>
          <Empire_Name>The Enslavers</Empire_Name>
          <Source>Core</Source>
        </race>
        <difficulty>0</difficulty>
        <startThreat>0</startThreat>
        <colour>
          <r>0.9056604</r>
          <g>0.890356541</g>
          <b>0</b>
          <a>1</a>
        </colour>
        <nPlanets>5</nPlanets>
      </AI_Class>
    </toggledAI>
    <trooperNamesList>American Names</trooperNamesList>
    <playerColours>
      <Color32>
        <r>202</r>
        <g>0</g>
        <b>0</b>
        <a>255</a>
      </Color32>
      <Color32>
        <r>0</r>
        <g>36</g>
        <b>214</b>
        <a>255</a>
      </Color32>
      <Color32>
        <r>0</r>
        <g>255</g>
        <b>37</b>
        <a>255</a>
      </Color32>
      <Color32>
        <r>147</r>
        <g>147</g>
        <b>147</b>
        <a>255</a>
      </Color32>
      <Color32>
        <r>241</r>
        <g>255</g>
        <b>0</b>
        <a>255</a>
      </Color32>
      <Color32>
        <r>202</r>
        <g>0</g>
        <b>0</b>
        <a>255</a>
      </Color32>
      <Color32>
        <r>0</r>
        <g>36</g>
        <b>214</b>
        <a>255</a>
      </Color32>
      <Color32>
        <r>0</r>
        <g>255</g>
        <b>37</b>
        <a>255</a>
      </Color32>
      <Color32>
        <r>147</r>
        <g>147</g>
        <b>147</b>
        <a>255</a>
      </Color32>
      <Color32>
        <r>241</r>
        <g>255</g>
        <b>0</b>
        <a>255</a>
      </Color32>
      <Color32>
        <r>202</r>
        <g>0</g>
        <b>0</b>
        <a>255</a>
      </Color32>
      <Color32>
        <r>0</r>
        <g>36</g>
        <b>214</b>
        <a>255</a>
      </Color32>
      <Color32>
        <r>0</r>
        <g>255</g>
        <b>37</b>
        <a>255</a>
      </Color32>
      <Color32>
        <r>147</r>
        <g>147</g>
        <b>147</b>
        <a>255</a>
      </Color32>
    </playerColours>
  </generatedProduct>
  <topSlots>
    <Slot_Class>
      <containedSlots>
        <Slot_Class>
          <containedSlots>
            <Slot_Class>
              <containedSlots>
                <Slot_Class>
                  <containedSlots />
                  <containedTroopers>
                    <Trooper_Class>
                      <trooperName>Ellis Nicholes</trooperName>
                      <trooperRank>Private</trooperRank>
                      <trooperFace>3</trooperFace>
                      <trooperHair>2</trooperHair>
                      <hairColour>0</hairColour>
                      <gender>1</gender>
                      <trooperPosition>1</trooperPosition>
                    </Trooper_Class>
                    <Trooper_Class>
                      <trooperName>Paige Spencer</trooperName>
                      <trooperRank>Private</trooperRank>
                      <trooperFace>7</trooperFace>
                      <trooperHair>1</trooperHair>
                      <hairColour>0</hairColour>
                      <gender>0</gender>
                      <trooperPosition>2</trooperPosition>
                    </Trooper_Class>
                    <Trooper_Class>
                      <trooperName>Georgina Queer</trooperName>
                      <trooperRank>Private</trooperRank>
                      <trooperFace>3</trooperFace>
                      <trooperHair>0</trooperHair>
                      <hairColour>9</hairColour>
                      <gender>0</gender>
                      <trooperPosition>3</trooperPosition>
                    </Trooper_Class>
                    <Trooper_Class>
                      <trooperName>Ella Elliott</trooperName>
                      <trooperRank>Private</trooperRank>
                      <trooperFace>3</trooperFace>
                      <trooperHair>0</trooperHair>
                      <hairColour>7</hairColour>
                      <gender>0</gender>
                      <trooperPosition>4</trooperPosition>
                    </Trooper_Class>
                    <Trooper_Class>
                      <trooperName>Layla Harris</trooperName>
                      <trooperRank>Private</trooperRank>
                      <trooperFace>1</trooperFace>
                      <trooperHair>1</trooperHair>
                      <hairColour>4</hairColour>
                      <gender>0</gender>
                      <trooperPosition>5</trooperPosition>
                    </Trooper_Class>
                    <Trooper_Class>
                      <trooperName>Louie Murphy</trooperName>
                      <trooperRank>Private</trooperRank>
                      <trooperFace>3</trooperFace>
                      <trooperHair>2</trooperHair>
                      <hairColour>2</hairColour>
                      <gender>1</gender>
                      <trooperPosition>6</trooperPosition>
                    </Trooper_Class>
                    <Trooper_Class>
                      <trooperName>Daisy Fisher</trooperName>
                      <trooperRank>Private</trooperRank>
                      <trooperFace>3</trooperFace>
                      <trooperHair>1</trooperHair>
                      <hairColour>3</hairColour>
                      <gender>0</gender>
                      <trooperPosition>7</trooperPosition>
                    </Trooper_Class>
                    <Trooper_Class>
                      <trooperName>Luke Fisher</trooperName>
                      <trooperRank>Private</trooperRank>
                      <trooperFace>2</trooperFace>
                      <trooperHair>1</trooperHair>
                      <hairColour>5</hairColour>
                      <gender>1</gender>
                      <trooperPosition>8</trooperPosition>
                    </Trooper_Class>
                    <Trooper_Class>
                      <trooperName>Edward Young</trooperName>
                      <trooperRank>Private</trooperRank>
                      <trooperFace>3</trooperFace>
                      <trooperHair>1</trooperHair>
                      <hairColour>8</hairColour>
                      <gender>1</gender>
                      <trooperPosition>9</trooperPosition>
                    </Trooper_Class>
                    <Trooper_Class>
                      <trooperName>Ivy Bennett</trooperName>
                      <trooperRank>Private</trooperRank>
                      <trooperFace>4</trooperFace>
                      <trooperHair>0</trooperHair>
                      <hairColour>4</hairColour>
                      <gender>0</gender>
                      <trooperPosition>10</trooperPosition>
                    </Trooper_Class>
                  </containedTroopers>
                  <slotName>1st Section</slotName>
                  <positionID>0</positionID>
                  <squad>true</squad>
                  <numberOfTroopers>10</numberOfTroopers>
                  <slotHeight>3</slotHeight>
                </Slot_Class>
                <Slot_Class>
                  <containedSlots />
                  <containedTroopers>
                    <Trooper_Class>
                      <trooperName>Florence Idle</trooperName>
                      <trooperRank>Private</trooperRank>
                      <trooperFace>7</trooperFace>
                      <trooperHair>1</trooperHair>
                      <hairColour>2</hairColour>
                      <gender>0</gender>
                      <trooperPosition>1</trooperPosition>
                    </Trooper_Class>
                    <Trooper_Class>
                      <trooperName>Isabella Addington</trooperName>
                      <trooperRank>Private</trooperRank>
                      <trooperFace>5</trooperFace>
                      <trooperHair>0</trooperHair>
                      <hairColour>5</hairColour>
                      <gender>0</gender>
                      <trooperPosition>2</trooperPosition>
                    </Trooper_Class>
                    <Trooper_Class>
                      <trooperName>Victor Taylor</trooperName>
                      <trooperRank>Private</trooperRank>
                      <trooperFace>6</trooperFace>
                      <trooperHair>0</trooperHair>
                      <hairColour>9</hairColour>
                      <gender>1</gender>
                      <trooperPosition>3</trooperPosition>
                    </Trooper_Class>
                    <Trooper_Class>
                      <trooperName>David Jones</trooperName>
                      <trooperRank>Private</trooperRank>
                      <trooperFace>2</trooperFace>
                      <trooperHair>2</trooperHair>
                      <hairColour>2</hairColour>
                      <gender>1</gender>
                      <trooperPosition>4</trooperPosition>
                    </Trooper_Class>
                    <Trooper_Class>
                      <trooperName>Abigail Kerbain</trooperName>
                      <trooperRank>Private</trooperRank>
                      <trooperFace>1</trooperFace>
                      <trooperHair>0</trooperHair>
                      <hairColour>9</hairColour>
                      <gender>0</gender>
                      <trooperPosition>5</trooperPosition>
                    </Trooper_Class>
                    <Trooper_Class>
                      <trooperName>Seth King</trooperName>
                      <trooperRank>Private</trooperRank>
                      <trooperFace>4</trooperFace>
                      <trooperHair>0</trooperHair>
                      <hairColour>3</hairColour>
                      <gender>1</gender>
                      <trooperPosition>6</trooperPosition>
                    </Trooper_Class>
                    <Trooper_Class>
                      <trooperName>James Valor</trooperName>
                      <trooperRank>Private</trooperRank>
                      <trooperFace>6</trooperFace>
                      <trooperHair>1</trooperHair>
                      <hairColour>7</hairColour>
                      <gender>1</gender>
                      <trooperPosition>7</trooperPosition>
                    </Trooper_Class>
                    <Trooper_Class>
                      <trooperName>Charlie Miller</trooperName>
                      <trooperRank>Private</trooperRank>
                      <trooperFace>5</trooperFace>
                      <trooperHair>1</trooperHair>
                      <hairColour>0</hairColour>
                      <gender>1</gender>
                      <trooperPosition>8</trooperPosition>
                    </Trooper_Class>
                    <Trooper_Class>
                      <trooperName>Nancy Henderson</trooperName>
                      <trooperRank>Private</trooperRank>
                      <trooperFace>7</trooperFace>
                      <trooperHair>1</trooperHair>
                      <hairColour>2</hairColour>
                      <gender>0</gender>
                      <trooperPosition>9</trooperPosition>
                    </Trooper_Class>
                    <Trooper_Class>
                      <trooperName>Masie Wood</trooperName>
                      <trooperRank>Private</trooperRank>
                      <trooperFace>6</trooperFace>
                      <trooperHair>1</trooperHair>
                      <hairColour>4</hairColour>
                      <gender>0</gender>
                      <trooperPosition>10</trooperPosition>
                    </Trooper_Class>
                  </containedTroopers>
                  <slotName>2nd Section</slotName>
                  <positionID>0</positionID>
                  <squad>true</squad>
                  <numberOfTroopers>10</numberOfTroopers>
                  <slotHeight>3</slotHeight>
                </Slot_Class>
                <Slot_Class>
                  <containedSlots />
                  <containedTroopers>
                    <Trooper_Class>
                      <trooperName>Finley Rogers</trooperName>
                      <trooperRank>Private</trooperRank>
                      <trooperFace>2</trooperFace>
                      <trooperHair>1</trooperHair>
                      <hairColour>0</hairColour>
                      <gender>1</gender>
                      <trooperPosition>1</trooperPosition>
                    </Trooper_Class>
                    <Trooper_Class>
                      <trooperName>Charlotte Abbot</trooperName>
                      <trooperRank>Private</trooperRank>
                      <trooperFace>3</trooperFace>
                      <trooperHair>1</trooperHair>
                      <hairColour>9</hairColour>
                      <gender>0</gender>
                      <trooperPosition>2</trooperPosition>
                    </Trooper_Class>
                    <Trooper_Class>
                      <trooperName>Will Yank</trooperName>
                      <trooperRank>Private</trooperRank>
                      <trooperFace>4</trooperFace>
                      <trooperHair>2</trooperHair>
                      <hairColour>2</hairColour>
                      <gender>1</gender>
                      <trooperPosition>3</trooperPosition>
                    </Trooper_Class>
                    <Trooper_Class>
                      <trooperName>Aaron OBryan</trooperName>
                      <trooperRank>Private</trooperRank>
                      <trooperFace>7</trooperFace>
                      <trooperHair>0</trooperHair>
                      <hairColour>1</hairColour>
                      <gender>1</gender>
                      <trooperPosition>4</trooperPosition>
                    </Trooper_Class>
                    <Trooper_Class>
                      <trooperName>Harrison Ford</trooperName>
                      <trooperRank>Private</trooperRank>
                      <trooperFace>1</trooperFace>
                      <trooperHair>0</trooperHair>
                      <hairColour>7</hairColour>
                      <gender>0</gender>
                      <trooperPosition>5</trooperPosition>
                    </Trooper_Class>
                    <Trooper_Class>
                      <trooperName>James Reid</trooperName>
                      <trooperRank>Private</trooperRank>
                      <trooperFace>1</trooperFace>
                      <trooperHair>0</trooperHair>
                      <hairColour>8</hairColour>
                      <gender>1</gender>
                      <trooperPosition>6</trooperPosition>
                    </Trooper_Class>
                    <Trooper_Class>
                      <trooperName>Matilda Foster</trooperName>
                      <trooperRank>Private</trooperRank>
                      <trooperFace>5</trooperFace>
                      <trooperHair>0</trooperHair>
                      <hairColour>4</hairColour>
                      <gender>0</gender>
                      <trooperPosition>7</trooperPosition>
                    </Trooper_Class>
                    <Trooper_Class>
                      <trooperName>Bethany Dawson</trooperName>
                      <trooperRank>Private</trooperRank>
                      <trooperFace>3</trooperFace>
                      <trooperHair>0</trooperHair>
                      <hairColour>3</hairColour>
                      <gender>0</gender>
                      <trooperPosition>8</trooperPosition>
                    </Trooper_Class>
                    <Trooper_Class>
                      <trooperName>Theo Kelly</trooperName>
                      <trooperRank>Private</trooperRank>
                      <trooperFace>3</trooperFace>
                      <trooperHair>2</trooperHair>
                      <hairColour>8</hairColour>
                      <gender>1</gender>
                      <trooperPosition>9</trooperPosition>
                    </Trooper_Class>
                    <Trooper_Class>
                      <trooperName>Samuel Phillips</trooperName>
                      <trooperRank>Private</trooperRank>
                      <trooperFace>6</trooperFace>
                      <trooperHair>1</trooperHair>
                      <hairColour>5</hairColour>
                      <gender>1</gender>
                      <trooperPosition>10</trooperPosition>
                    </Trooper_Class>
                  </containedTroopers>
                  <slotName>3rd Section</slotName>
                  <positionID>0</positionID>
                  <squad>true</squad>
                  <numberOfTroopers>10</numberOfTroopers>
                  <slotHeight>3</slotHeight>
                </Slot_Class>
              </containedSlots>
              <containedTroopers />
              <slotName>1st Squad</slotName>
              <positionID>0</positionID>
              <squad>false</squad>
              <numberOfTroopers>0</numberOfTroopers>
              <slotHeight>2</slotHeight>
            </Slot_Class>
          </containedSlots>
          <containedTroopers />
          <slotName>1st Platoon</slotName>
          <positionID>0</positionID>
          <squad>false</squad>
          <numberOfTroopers>0</numberOfTroopers>
          <slotHeight>1</slotHeight>
        </Slot_Class>
        <Slot_Class>
          <containedSlots />
          <containedTroopers />
          <slotName>2nd Platoon</slotName>
          <positionID>0</positionID>
          <squad>false</squad>
          <numberOfTroopers>0</numberOfTroopers>
          <slotHeight>1</slotHeight>
        </Slot_Class>
        <Slot_Class>
          <containedSlots />
          <containedTroopers />
          <slotName>3rd Platoon</slotName>
          <positionID>0</positionID>
          <squad>false</squad>
          <numberOfTroopers>0</numberOfTroopers>
          <slotHeight>1</slotHeight>
        </Slot_Class>
        <Slot_Class>
          <containedSlots />
          <containedTroopers />
          <slotName>4th Platoon</slotName>
          <positionID>0</positionID>
          <squad>false</squad>
          <numberOfTroopers>0</numberOfTroopers>
          <slotHeight>1</slotHeight>
        </Slot_Class>
        <Slot_Class>
          <containedSlots />
          <containedTroopers />
          <slotName>5th Platoon</slotName>
          <positionID>0</positionID>
          <squad>false</squad>
          <numberOfTroopers>0</numberOfTroopers>
          <slotHeight>1</slotHeight>
        </Slot_Class>
        <Slot_Class>
          <containedSlots />
          <containedTroopers />
          <slotName>6th Platoon</slotName>
          <positionID>0</positionID>
          <squad>false</squad>
          <numberOfTroopers>0</numberOfTroopers>
          <slotHeight>1</slotHeight>
        </Slot_Class>
      </containedSlots>
      <containedTroopers />
      <slotName>1st Company</slotName>
      <positionID>0</positionID>
      <squad>false</squad>
      <numberOfTroopers>0</numberOfTroopers>
      <slotHeight>0</slotHeight>
    </Slot_Class>
  </topSlots>
</Save_Class>